Tracker_HSV/__init__.py
Tracker_HSV-0.0.3.dist-info/LICENSE.txt
Tracker_HSV-0.0.3.dist-info/METADATA
Tracker_HSV-0.0.3.dist-info/WHEEL
Tracker_HSV-0.0.3.dist-info/top_level.txt
Tracker_HSV-0.0.3.dist-info/RECORD
