Metadata-Version: 2.1
Name: Tracker-HSV
Version: 0.0.3
Summary: Tracker for HSV
Home-page: https://github.com/Pushkar-Singh-14/Tracker_HSV
Author: Pushkar Singh
Author-email: pushkar7722@gmail.com.com
License: UNKNOWN
Platform: UNKNOWN
Classifier: Programming Language :: Python :: 3
Classifier: License :: OSI Approved :: MIT License
Classifier: Operating System :: OS Independent
